odoo/addons/account_cutoff_picking/README.rst
odoo/addons/account_cutoff_picking/__init__.py
odoo/addons/account_cutoff_picking/__manifest__.py
odoo/addons/account_cutoff_picking/i18n/account_cutoff_picking.pot
odoo/addons/account_cutoff_picking/i18n/de.po
odoo/addons/account_cutoff_picking/i18n/es.po
odoo/addons/account_cutoff_picking/i18n/fr.po
odoo/addons/account_cutoff_picking/i18n/fr_BE.po
odoo/addons/account_cutoff_picking/i18n/it.po
odoo/addons/account_cutoff_picking/i18n/sv.po
odoo/addons/account_cutoff_picking/images/accrued_expense_done.jpg
odoo/addons/account_cutoff_picking/images/accrued_expense_draft.jpg
odoo/addons/account_cutoff_picking/images/accrued_expense_journal_entry.jpg
odoo/addons/account_cutoff_picking/models/__init__.py
odoo/addons/account_cutoff_picking/models/account_cutoff.py
odoo/addons/account_cutoff_picking/models/res_company.py
odoo/addons/account_cutoff_picking/readme/CONFIGURE.md
odoo/addons/account_cutoff_picking/readme/CONTRIBUTORS.md
odoo/addons/account_cutoff_picking/readme/CREDITS.md
odoo/addons/account_cutoff_picking/readme/DESCRIPTION.md
odoo/addons/account_cutoff_picking/static/description/icon.png
odoo/addons/account_cutoff_picking/static/description/index.html
odoo/addons/account_cutoff_picking/static/src/img/icon.png
odoo/addons/account_cutoff_picking/views/account_cutoff.xml
odoo/addons/account_cutoff_picking/views/res_config_settings.xml
odoo/addons/account_cutoff_picking/wizards/__init__.py
odoo/addons/account_cutoff_picking/wizards/res_config_settings.py
odoo_addon_account_cutoff_picking-18.0.1.0.0.2.dist-info/METADATA
odoo_addon_account_cutoff_picking-18.0.1.0.0.2.dist-info/WHEEL
odoo_addon_account_cutoff_picking-18.0.1.0.0.2.dist-info/top_level.txt
odoo_addon_account_cutoff_picking-18.0.1.0.0.2.dist-info/RECORD
